hanzo_tools/__init__.py
hanzo_tools/api/__init__.py
hanzo_tools/api/api_tool.py
hanzo_tools/api/apis_guru_providers.py
hanzo_tools/api/client.py
hanzo_tools/api/credentials.py
hanzo_tools/api/errors.py
hanzo_tools/api/models.py
hanzo_tools/api/openapi_client.py
hanzo_tools/api/providers.py
hanzo_tools/api/storage.py
hanzo_tools_api-0.3.1.dist-info/METADATA
hanzo_tools_api-0.3.1.dist-info/WHEEL
hanzo_tools_api-0.3.1.dist-info/entry_points.txt
hanzo_tools_api-0.3.1.dist-info/RECORD
