Metadata-Version: 2.4
Name: hanzo-tools-api
Version: 0.3.1
Summary: Generic API tool for calling any REST API via OpenAPI specs - search, explore, and dynamically use ANY API
Author-email: Hanzo AI <dev@hanzo.ai>
License: MIT
Keywords: api,hanzo,mcp,openapi,tools
Classifier: Development Status :: 4 - Beta
Classifier: Intended Audience :: Developers
Classifier: License :: OSI Approved :: MIT License
Classifier: Programming Language :: Python :: 3.12
Classifier: Programming Language :: Python :: 3.13
Requires-Python: >=3.12
Requires-Dist: aiofiles>=24.1.0
Requires-Dist: hanzo-tools-core>=0.1.0
Requires-Dist: httpx>=0.27.0
Requires-Dist: pydantic>=2.0
Requires-Dist: pyyaml>=6.0
Provides-Extra: dev
Requires-Dist: pytest-asyncio>=0.24.0; extra == 'dev'
Requires-Dist: pytest>=8.0; extra == 'dev'
Requires-Dist: respx>=0.22.0; extra == 'dev'
